neoaccess/__init__.py
neoaccess/cypher_utils.py
neoaccess/neoaccess.py
neoaccess-4.4.2.dist-info/METADATA
neoaccess-4.4.2.dist-info/WHEEL
neoaccess-4.4.2.dist-info/licenses/LICENSE.txt
neoaccess-4.4.2.dist-info/RECORD
